[{"goods": "26003800E370KT2", "hist_rate": 33.3, "recent_rate": 33.3, "delta": 0.0, "total_orders": 6, "recent_orders": 3, "is_alert": false}, {"goods": "26005800E492KT2", "hist_rate": 28.6, "recent_rate": 33.3, "delta": 4.8, "total_orders": 24, "recent_orders": 3, "is_alert": true}, {"goods": "25010800E432KT2", "hist_rate": 32.5, "recent_rate": 20.0, "delta": -12.5, "total_orders": 442, "recent_orders": 5, "is_alert": false}, {"goods": "26013400E370KT2", "hist_rate": 36.4, "recent_rate": 15.4, "delta": -21.0, "total_orders": 145, "recent_orders": 13, "is_alert": false}, {"goods": "26003300E353KT2", "hist_rate": 16.7, "recent_rate": 0.0, "delta": -16.7, "total_orders": 9, "recent_orders": 3, "is_alert": false}, {"goods": "24049700E307KT2", "hist_rate": 35.8, "recent_rate": 0.0, "delta": -35.8, "total_orders": 373, "recent_orders": 10, "is_alert": false}, {"goods": "26002800E324KT1", "hist_rate": 0.0, "recent_rate": 0.0, "delta": 0.0, "total_orders": 14, "recent_orders": 4, "is_alert": false}, {"goods": "25019200E362PT3", "hist_rate": 18.2, "recent_rate": 0.0, "delta": -18.2, "total_orders": 15, "recent_orders": 4, "is_alert": false}, {"goods": "24035800E370KT2", "hist_rate": 34.3, "recent_rate": 0.0, "delta": -34.3, "total_orders": 140, "recent_orders": 3, "is_alert": false}, {"goods": "260193B1E301KT2", "hist_rate": 42.1, "recent_rate": 0.0, "delta": -42.1, "total_orders": 22, "recent_orders": 3, "is_alert": false}]